[
 {
   "file_name": "IMG_0759.JPG",
   "longitude": 40.7615,
   "latitude": -73.9777,
   "time": "2018.3.12 16:10",
   "content": "life"
 },
 {
   "file_name": "IMG_0751.JPG",
   "longitude": 40.7614,
   "latitude": -73.9764,
   "time": "2018.3.12 16:19",
   "content": "life"
 },
 {
   "file_name": "IMG_0761.JPG",
   "longitude": 40.7615,
   "latitude": -73.9765,
   "time": "2018.3.12 16:25",
   "content": "life"
 },
 {
   "file_name": "IMG_0782.JPG",
   "longitude": 40.7298,
   "latitude": -73.9968,
   "time": "2018.3.14 12:15",
   "content": "life"
 },
 {
   "file_name": "IMG_0785.JPG",
   "longitude": 40.7298,
   "latitude": -73.9968,
   "time": "2018.3.14 17:50",
   "content": "work"
 },
 {
   "file_name": "IMG_0856.JPG",
   "longitude": 40.7298,
   "latitude": -73.9969,
   "time": "2018.3.19 12:24",
   "content": "food"
 },
 {
   "file_name": "IMG_0857.JPG",
   "longitude": 40.7298,
   "latitude": -73.9969,
   "time": "2018.3.19 12:24",
   "content": "work"
 },
 {
   "file_name": "IMG_0858.JPG",
   "longitude": 40.7298,
   "latitude": -73.9969,
   "time": "2018.3.19 12:25",
   "content": "food"
 },
 {
   "file_name": "IMG_0873.JPG",
   "longitude": 40.7197,
   "latitude": -74.0351,
   "time": "2018.3.21 10:41",
   "content": "life"
 },
 {
   "file_name": "IMG_0880.JPG",
   "longitude": 40.7199,
   "latitude": -74.0351,
   "time": "2018.3.22 13:40",
   "content": "life"
 },
 {
   "file_name": "IMG_0882.JPG",
   "longitude": 40.7196,
   "latitude": -74.0351,
   "time": "2018.3.22 15:38",
   "content": "food"
 },
 {
   "file_name": "IMG_0852.JPG",
   "longitude": 40.7298,
   "latitude": -73.9969,
   "time": "2018.3.23 11:24",
   "content": "work"
 },
 {
   "file_name": "IMG_0861 2.JPG",
   "longitude": 40.7298,
   "latitude": -73.9936,
   "time": "2018.3.23 11:25",
   "content": "work"
 },
 {
   "file_name": "IMG_0867.JPG",
   "longitude": 40.7196,
   "latitude": -74.0353,
   "time": "2018.3.23 11:26",
   "content": "selfie"
 },
 {
   "file_name": "IMG_0884.JPG",
   "longitude": 40.7298,
   "latitude": -73.9969,
   "time": "2018.3.23 11:41",
   "content": "food"
 }
]
